nbprune/__init__.py
nbprune/nbprune.py
nbprune/version.py
nbprune-0.5.3.dist-info/METADATA
nbprune-0.5.3.dist-info/WHEEL
nbprune-0.5.3.dist-info/entry_points.txt
nbprune-0.5.3.dist-info/RECORD
