Metadata-Version: 2.4
Name: nbprune
Version: 0.5.3
Summary: With this tool, one can define pieces of a notebook that belong to teachers and should not be exposed to students.
Project-URL: Repository, https://github.com/flotpython/nbprune
Project-URL: Bug Tracker, https://github.com/flotpython/nbprune/issues
Author-email: Thierry Parmentelat <thierry.parmentelat@minesparis.psl.eu>
License: MIT License
Keywords: education,jupyter,notebook,teaching
Requires-Python: >=3.8
Requires-Dist: jupytext
